indico
indico_zodbimport
